armaqdl/__init__.py
armaqdl/__main__.py
armaqdl/_version.py
armaqdl/armaqdl.py
armaqdl/config.py
armaqdl/const.py
armaqdl/update.py
armaqdl/config/settings.toml
armaqdl-1.0.0.dist-info/METADATA
armaqdl-1.0.0.dist-info/WHEEL
armaqdl-1.0.0.dist-info/entry_points.txt
armaqdl-1.0.0.dist-info/licenses/LICENSE
armaqdl-1.0.0.dist-info/RECORD
