Metadata-Version: 2.3
Name: ArmaQDL
Version: 1.0.0
Summary: Python program for quick launching various mod development configurations for Arma through a simple CLI.
Project-URL: Homepage, https://github.com/jonpas/Arma-QDL
Project-URL: Bug Tracker, https://github.com/jonpas/Arma-QDL/issues
Author-email: Jonpas <jonpas33@gmail.com>
License-Expression: MIT
License-File: LICENSE
Classifier: Environment :: Console
Classifier: Intended Audience :: Developers
Classifier: License :: OSI Approved :: MIT License
Classifier: Operating System :: Microsoft :: Windows
Classifier: Programming Language :: Python :: 3.8
Classifier: Programming Language :: Python :: 3.9
Classifier: Programming Language :: Python :: 3.10
Classifier: Programming Language :: Python :: 3.11
Classifier: Programming Language :: Python :: 3.12
Classifier: Topic :: Software Development :: Build Tools
Requires-Python: >=3.8
Requires-Dist: platformdirs
Requires-Dist: toml
